layer_packaging/__init__.py
layer_packaging/build_layers.py
layer_packaging/release_manifest.py
layer_packaging/runtime_loader.py
layer_packaging-0.1.20.dist-info/METADATA
layer_packaging-0.1.20.dist-info/WHEEL
layer_packaging-0.1.20.dist-info/entry_points.txt
layer_packaging-0.1.20.dist-info/licenses/LICENCE
layer_packaging-0.1.20.dist-info/RECORD
