Metadata-Version: 2.4
Name: layer-packaging
Version: 0.1.20
Summary: Packages dependencies and code in layers
Author-email: Mitchell Needham <contact@mitchellneedham.com>
License-Expression: MIT
License-File: LICENCE
Classifier: Operating System :: Microsoft :: Windows
Classifier: Programming Language :: Python :: 3
Requires-Python: >=3.12
